vizdet/__init__.py
vizdet/bboxes.py
vizdet/font.py
vizdet/infobox.py
vizdet/label.py
vizdet/fonts/FiraGO-Regular.ttf
vizdet-0.1.8.dist-info/LICENSE
vizdet-0.1.8.dist-info/METADATA
vizdet-0.1.8.dist-info/WHEEL
vizdet-0.1.8.dist-info/top_level.txt
vizdet-0.1.8.dist-info/RECORD
