Metadata-Version: 2.1
Name: vizdet
Version: 0.1.8
Summary: Vizualization for Detection and Tracking
Home-page: https://github.com/tadejsv/vizdet
Author: Tadej Svetina
License: Apache-2.0 License
Keywords: visualization,tracking,object detection,computer vision
Platform: UNKNOWN
Classifier: License :: OSI Approved :: Apache Software License
Classifier: Programming Language :: Python :: 3
Classifier: Programming Language :: Python :: 3.7
Classifier: Programming Language :: Python :: 3.8
Classifier: Programming Language :: Python :: 3.9
Classifier: Development Status :: 3 - Alpha
Classifier: Topic :: Scientific/Engineering :: Image Recognition
Requires-Python: >=3.7
License-File: LICENSE
Requires-Dist: numpy
Provides-Extra: docs
Requires-Dist: Sphinx ; extra == 'docs'
Requires-Dist: pydata-sphinx-theme ; extra == 'docs'
Requires-Dist: sphinx-autodoc-typehints ; extra == 'docs'
Provides-Extra: tests
Requires-Dist: pytest ; extra == 'tests'
Requires-Dist: flake8 ; extra == 'tests'
Requires-Dist: black ; extra == 'tests'
Requires-Dist: mypy ; extra == 'tests'
Requires-Dist: isort ; extra == 'tests'
